{
  "actionGroups" : [ "general", "melee_dps", "ranged_dps", "healer", "caster_dps", "tank", "marauder", "warrior", "gladiator", "paladin", "pugilist", "monk", "lancer", "dragoon", "archer", "bard", "conjurer", "white_mage", "thaumaturge", "black_mage", "arcanist", "summoner", "garuda-egi", "titan-egi", "ifrit-egi", "pets", "arcanist", "scholar", "eos", "selene", "rogue", "ninja", "dark_knight", "astrologian", "machinist", "samurai", "red_mage" ],
  "actions" : {
    "1" : {
      "icon" : "000104.png",
      "id" : "1",
      "job" : "general",
      "levelReq" : "1",
      "name" : "Sprint"
    },
    "2" : {
      "icon" : "000103.png",
      "id" : "2",
      "job" : "general",
      "levelReq" : "15",
      "name" : "Limit Break"
    },
    "9" : {
      "classCategory" : "38",
      "icon" : "000158.png",
      "id" : "9",
      "job" : "gladiator",
      "levelReq" : "1",
      "name" : "Fast Blade"
    },
    "11" : {
      "classCategory" : "38",
      "icon" : "000157.png",
      "id" : "11",
      "job" : "gladiator",
      "levelReq" : "4",
      "name" : "Savage Blade"
    },
    "14" : {
      "classCategory" : "38",
      "icon" : "000159.png",
      "id" : "14",
      "job" : "gladiator",
      "levelReq" : "6",
      "name" : "Flash"
    },
    "15" : {
      "classCategory" : "38",
      "icon" : "000156.png",
      "id" : "15",
      "job" : "gladiator",
      "levelReq" : "10",
      "name" : "Riot Blade"
    },
    "16" : {
      "classCategory" : "38",
      "icon" : "000154.png",
      "id" : "16",
      "job" : "gladiator",
      "levelReq" : "18",
      "name" : "Shield Bash"
    },
    "17" : {
      "classCategory" : "38",
      "icon" : "000151.png",
      "id" : "17",
      "job" : "gladiator",
      "levelReq" : "38",
      "name" : "Sentinel"
    },
    "19" : {
      "classCategory" : "38",
      "icon" : "000153.png",
      "id" : "19",
      "job" : "gladiator",
      "levelReq" : "42",
      "name" : "Tempered Will"
    },
    "20" : {
      "classCategory" : "38",
      "icon" : "000166.png",
      "id" : "20",
      "job" : "gladiator",
      "levelReq" : "2",
      "name" : "Fight or Flight"
    },
    "21" : {
      "classCategory" : "38",
      "icon" : "000155.png",
      "id" : "21",
      "job" : "gladiator",
      "levelReq" : "26",
      "name" : "Rage of Halone"
    },
    "22" : {
      "classCategory" : "38",
      "icon" : "000167.png",
      "id" : "22",
      "job" : "gladiator",
      "levelReq" : "46",
      "name" : "Bulwark"
    },
    "23" : {
      "classCategory" : "38",
      "icon" : "000161.png",
      "id" : "23",
      "job" : "gladiator",
      "levelReq" : "50",
      "name" : "Circle of Scorn"
    },
    "24" : {
      "classCategory" : "38",
      "icon" : "000164.png",
      "id" : "24",
      "job" : "gladiator",
      "levelReq" : "15",
      "name" : "Shield Lob"
    },
    "25" : {
      "classCategory" : "38",
      "icon" : "000160.png",
      "id" : "25",
      "job" : "gladiator",
      "levelReq" : "30",
      "name" : "Shield Swipe"
    },
    "26" : {
      "classCategory" : "20",
      "icon" : "002504.png",
      "id" : "26",
      "job" : "paladin",
      "levelReq" : "35",
      "name" : "Sword Oath"
    },
    "27" : {
      "classCategory" : "20",
      "icon" : "002501.png",
      "id" : "27",
      "job" : "paladin",
      "levelReq" : "40",
      "name" : "Cover"
    },
    "28" : {
      "classCategory" : "20",
      "icon" : "002505.png",
      "id" : "28",
      "job" : "paladin",
      "levelReq" : "30",
      "name" : "Shield Oath"
    },
    "29" : {
      "classCategory" : "20",
      "icon" : "002503.png",
      "id" : "29",
      "job" : "paladin",
      "levelReq" : "45",
      "name" : "Spirits Within"
    },
    "30" : {
      "classCategory" : "20",
      "icon" : "002502.png",
      "id" : "30",
      "job" : "paladin",
      "levelReq" : "50",
      "name" : "Hallowed Ground"
    },
    "31" : {
      "classCategory" : "44",
      "icon" : "000260.png",
      "id" : "31",
      "job" : "marauder",
      "levelReq" : "1",
      "name" : "Heavy Swing"
    },
    "35" : {
      "classCategory" : "44",
      "icon" : "000257.png",
      "id" : "35",
      "job" : "marauder",
      "levelReq" : "4",
      "name" : "Skull Sunder"
    },
    "37" : {
      "classCategory" : "44",
      "icon" : "000255.png",
      "id" : "37",
      "job" : "marauder",
      "levelReq" : "18",
      "name" : "Maim"
    },
    "38" : {
      "classCategory" : "44",
      "icon" : "000259.png",
      "id" : "38",
      "job" : "marauder",
      "levelReq" : "6",
      "name" : "Berserk"
    },
    "40" : {
      "classCategory" : "44",
      "icon" : "000263.png",
      "id" : "40",
      "job" : "marauder",
      "levelReq" : "26",
      "name" : "Thrill of Battle"
    },
    "41" : {
      "classCategory" : "44",
      "icon" : "000254.png",
      "id" : "41",
      "job" : "marauder",
      "levelReq" : "10",
      "name" : "Overpower"
    },
    "42" : {
      "classCategory" : "44",
      "icon" : "000258.png",
      "id" : "42",
      "job" : "marauder",
      "levelReq" : "38",
      "name" : "Storm's Path"
    },
    "43" : {
      "classCategory" : "44",
      "icon" : "000266.png",
      "id" : "43",
      "job" : "marauder",
      "levelReq" : "42",
      "name" : "Holmgang"
    },
    "44" : {
      "classCategory" : "44",
      "icon" : "000267.png",
      "id" : "44",
      "job" : "marauder",
      "levelReq" : "46",
      "name" : "Vengeance"
    },
    "45" : {
      "classCategory" : "44",
      "icon" : "000264.png",
      "id" : "45",
      "job" : "marauder",
      "levelReq" : "50",
      "name" : "Storm's Eye"
    },
    "46" : {
      "classCategory" : "44",
      "icon" : "000261.png",
      "id" : "46",
      "job" : "marauder",
      "levelReq" : "15",
      "name" : "Tomahawk"
    },
    "47" : {
      "classCategory" : "44",
      "icon" : "000262.png",
      "id" : "47",
      "job" : "marauder",
      "levelReq" : "30",
      "name" : "Butcher's Block"
    },
    "48" : {
      "classCategory" : "22",
      "icon" : "002551.png",
      "id" : "48",
      "job" : "warrior",
      "levelReq" : "30",
      "name" : "Defiance"
    },
    "49" : {
      "classCategory" : "22",
      "icon" : "002553.png",
      "id" : "49",
      "job" : "warrior",
      "levelReq" : "35",
      "name" : "Inner Beast"
    },
    "50" : {
      "classCategory" : "22",
      "icon" : "002554.png",
      "id" : "50",
      "job" : "warrior",
      "levelReq" : "40",
      "name" : "Unchained"
    },
    "51" : {
      "classCategory" : "22",
      "icon" : "002552.png",
      "id" : "51",
      "job" : "warrior",
      "levelReq" : "45",
      "name" : "Steel Cyclone"
    },
    "52" : {
      "classCategory" : "22",
      "icon" : "002555.png",
      "id" : "52",
      "job" : "warrior",
      "levelReq" : "50",
      "name" : "Infuriate"
    },
    "53" : {
      "classCategory" : "41",
      "icon" : "000208.png",
      "id" : "53",
      "job" : "pugilist",
      "levelReq" : "1",
      "name" : "Bootshine"
    },
    "54" : {
      "classCategory" : "41",
      "icon" : "000209.png",
      "id" : "54",
      "job" : "pugilist",
      "levelReq" : "4",
      "name" : "True Strike"
    },
    "56" : {
      "classCategory" : "41",
      "icon" : "000210.png",
      "id" : "56",
      "job" : "pugilist",
      "levelReq" : "6",
      "name" : "Snap Punch"
    },
    "59" : {
      "classCategory" : "41",
      "icon" : "000212.png",
      "id" : "59",
      "job" : "pugilist",
      "levelReq" : "10",
      "name" : "Internal Release"
    },
    "60" : {
      "classCategory" : "41",
      "icon" : "000206.png",
      "id" : "60",
      "job" : "pugilist",
      "levelReq" : "15",
      "name" : "Fists of Earth"
    },
    "61" : {
      "classCategory" : "41",
      "icon" : "000213.png",
      "id" : "61",
      "job" : "pugilist",
      "levelReq" : "18",
      "name" : "Twin Snakes"
    },
    "62" : {
      "classCategory" : "41",
      "icon" : "000215.png",
      "id" : "62",
      "job" : "pugilist",
      "levelReq" : "26",
      "name" : "Arm of the Destroyer"
    },
    "63" : {
      "classCategory" : "21",
      "icon" : "000205.png",
      "id" : "63",
      "job" : "monk",
      "levelReq" : "40",
      "name" : "Fists of Fire"
    },
    "64" : {
      "classCategory" : "41",
      "icon" : "002530.png",
      "id" : "64",
      "job" : "pugilist",
      "levelReq" : "38",
      "name" : "Steel Peak"
    },
    "65" : {
      "classCategory" : "41",
      "icon" : "000216.png",
      "id" : "65",
      "job" : "pugilist",
      "levelReq" : "42",
      "name" : "Mantra"
    },
    "66" : {
      "classCategory" : "41",
      "icon" : "000204.png",
      "id" : "66",
      "job" : "pugilist",
      "levelReq" : "30",
      "name" : "Demolish"
    },
    "67" : {
      "classCategory" : "41",
      "icon" : "000207.png",
      "id" : "67",
      "job" : "pugilist",
      "levelReq" : "46",
      "name" : "Howling Fist"
    },
    "69" : {
      "classCategory" : "41",
      "icon" : "000217.png",
      "id" : "69",
      "job" : "pugilist",
      "levelReq" : "50",
      "name" : "Perfect Balance"
    },
    "70" : {
      "classCategory" : "21",
      "icon" : "002529.png",
      "id" : "70",
      "job" : "monk",
      "levelReq" : "30",
      "name" : "Rockbreaker"
    },
    "71" : {
      "classCategory" : "21",
      "icon" : "002526.png",
      "id" : "71",
      "job" : "monk",
      "levelReq" : "35",
      "name" : "Shoulder Tackle"
    },
    "72" : {
      "classCategory" : "21",
      "icon" : "000214.png",
      "id" : "72",
      "job" : "monk",
      "levelReq" : "45",
      "name" : "One Ilm Punch"
    },
    "73" : {
      "classCategory" : "41",
      "icon" : "002527.png",
      "id" : "73",
      "job" : "pugilist",
      "levelReq" : "34",
      "name" : "Fists of Wind"
    },
    "74" : {
      "classCategory" : "21",
      "icon" : "002528.png",
      "id" : "74",
      "job" : "monk",
      "levelReq" : "50",
      "name" : "Dragon Kick"
    },
    "75" : {
      "classCategory" : "47",
      "icon" : "000310.png",
      "id" : "75",
      "job" : "lancer",
      "levelReq" : "1",
      "name" : "True Thrust"
    },
    "78" : {
      "classCategory" : "47",
      "icon" : "000312.png",
      "id" : "78",
      "job" : "lancer",
      "levelReq" : "4",
      "name" : "Vorpal Thrust"
    },
    "79" : {
      "classCategory" : "47",
      "icon" : "000311.png",
      "id" : "79",
      "job" : "lancer",
      "levelReq" : "10",
      "name" : "Heavy Thrust"
    },
    "81" : {
      "classCategory" : "47",
      "icon" : "000313.png",
      "id" : "81",
      "job" : "lancer",
      "levelReq" : "6",
      "name" : "Impulse Drive"
    },
    "83" : {
      "classCategory" : "47",
      "icon" : "000304.png",
      "id" : "83",
      "job" : "lancer",
      "levelReq" : "18",
      "name" : "Life Surge"
    },
    "84" : {
      "classCategory" : "47",
      "icon" : "000314.png",
      "id" : "84",
      "job" : "lancer",
      "levelReq" : "26",
      "name" : "Full Thrust"
    },
    "85" : {
      "classCategory" : "47",
      "icon" : "000309.png",
      "id" : "85",
      "job" : "lancer",
      "levelReq" : "30",
      "name" : "Blood for Blood"
    },
    "86" : {
      "classCategory" : "23",
      "icon" : "000306.png",
      "id" : "86",
      "job" : "dragoon",
      "levelReq" : "40",
      "name" : "Doom Spike"
    },
    "87" : {
      "classCategory" : "47",
      "icon" : "000317.png",
      "id" : "87",
      "job" : "lancer",
      "levelReq" : "38",
      "name" : "Disembowel"
    },
    "88" : {
      "classCategory" : "47",
      "icon" : "000308.png",
      "id" : "88",
      "job" : "lancer",
      "levelReq" : "50",
      "name" : "Chaos Thrust"
    },
    "90" : {
      "classCategory" : "47",
      "icon" : "000315.png",
      "id" : "90",
      "job" : "lancer",
      "levelReq" : "15",
      "name" : "Piercing Talon"
    },
    "92" : {
      "classCategory" : "23",
      "icon" : "002576.png",
      "id" : "92",
      "job" : "dragoon",
      "levelReq" : "30",
      "name" : "Jump"
    },
    "94" : {
      "classCategory" : "23",
      "icon" : "002577.png",
      "id" : "94",
      "job" : "dragoon",
      "levelReq" : "35",
      "name" : "Elusive Jump"
    },
    "95" : {
      "classCategory" : "23",
      "icon" : "002580.png",
      "id" : "95",
      "job" : "dragoon",
      "levelReq" : "45",
      "name" : "Spineshatter Dive"
    },
    "96" : {
      "classCategory" : "23",
      "icon" : "002578.png",
      "id" : "96",
      "job" : "dragoon",
      "levelReq" : "50",
      "name" : "Dragonfire Dive"
    },
    "97" : {
      "classCategory" : "50",
      "icon" : "000358.png",
      "id" : "97",
      "job" : "archer",
      "levelReq" : "1",
      "name" : "Heavy Shot"
    },
    "98" : {
      "classCategory" : "50",
      "icon" : "000359.png",
      "id" : "98",
      "job" : "archer",
      "levelReq" : "2",
      "name" : "Straight Shot"
    },
    "100" : {
      "classCategory" : "50",
      "icon" : "000363.png",
      "id" : "100",
      "job" : "archer",
      "levelReq" : "6",
      "name" : "Venomous Bite"
    },
    "101" : {
      "classCategory" : "50",
      "icon" : "000352.png",
      "id" : "101",
      "job" : "archer",
      "levelReq" : "4",
      "name" : "Raging Strikes"
    },
    "103" : {
      "classCategory" : "50",
      "icon" : "000364.png",
      "id" : "103",
      "job" : "archer",
      "levelReq" : "10",
      "name" : "Misery's End"
    },
    "106" : {
      "classCategory" : "50",
      "icon" : "000360.png",
      "id" : "106",
      "job" : "archer",
      "levelReq" : "18",
      "name" : "Quick Nock"
    },
    "107" : {
      "classCategory" : "50",
      "icon" : "000353.png",
      "id" : "107",
      "job" : "archer",
      "levelReq" : "38",
      "name" : "Barrage"
    },
    "110" : {
      "classCategory" : "50",
      "icon" : "000361.png",
      "id" : "110",
      "job" : "archer",
      "levelReq" : "12",
      "name" : "Bloodletter"
    },
    "112" : {
      "classCategory" : "50",
      "icon" : "000366.png",
      "id" : "112",
      "job" : "archer",
      "levelReq" : "15",
      "name" : "Repelling Shot"
    },
    "113" : {
      "classCategory" : "50",
      "icon" : "000367.png",
      "id" : "113",
      "job" : "archer",
      "levelReq" : "30",
      "name" : "Windbite"
    },
    "114" : {
      "classCategory" : "24",
      "icon" : "002602.png",
      "id" : "114",
      "job" : "bard",
      "levelReq" : "30",
      "name" : "Mage's Ballad"
    },
    "115" : {
      "classCategory" : "24",
      "icon" : "002604.png",
      "id" : "115",
      "job" : "bard",
      "levelReq" : "35",
      "name" : "Foe Requiem"
    },
    "116" : {
      "classCategory" : "24",
      "icon" : "002603.png",
      "id" : "116",
      "job" : "bard",
      "levelReq" : "40",
      "name" : "Army's Paeon"
    },
    "117" : {
      "classCategory" : "24",
      "icon" : "002605.png",
      "id" : "117",
      "job" : "bard",
      "levelReq" : "45",
      "name" : "Rain of Death"
    },
    "118" : {
      "classCategory" : "24",
      "icon" : "002601.png",
      "id" : "118",
      "job" : "bard",
      "levelReq" : "50",
      "name" : "Battle Voice"
    },
    "119" : {
      "classCategory" : "53",
      "icon" : "000403.png",
      "id" : "119",
      "job" : "conjurer",
      "levelReq" : "1",
      "name" : "Stone"
    },
    "120" : {
      "classCategory" : "53",
      "icon" : "000405.png",
      "id" : "120",
      "job" : "conjurer",
      "levelReq" : "2",
      "name" : "Cure"
    },
    "121" : {
      "classCategory" : "53",
      "icon" : "000401.png",
      "id" : "121",
      "job" : "conjurer",
      "levelReq" : "4",
      "name" : "Aero"
    },
    "124" : {
      "classCategory" : "53",
      "icon" : "000408.png",
      "id" : "124",
      "job" : "conjurer",
      "levelReq" : "10",
      "name" : "Medica"
    },
    "125" : {
      "classCategory" : "53",
      "icon" : "000411.png",
      "id" : "125",
      "job" : "conjurer",
      "levelReq" : "12",
      "name" : "Raise"
    },
    "127" : {
      "classCategory" : "53",
      "icon" : "000404.png",
      "id" : "127",
      "job" : "conjurer",
      "levelReq" : "18",
      "name" : "Stone II"
    },
    "128" : {
      "classCategory" : "53",
      "icon" : "000414.png",
      "id" : "128",
      "job" : "conjurer",
      "levelReq" : "26",
      "name" : "Repose"
    },
    "131" : {
      "classCategory" : "25",
      "icon" : "000407.png",
      "id" : "131",
      "job" : "white_mage",
      "levelReq" : "40",
      "name" : "Cure III"
    },
    "132" : {
      "classCategory" : "53",
      "icon" : "000402.png",
      "id" : "132",
      "job" : "conjurer",
      "levelReq" : "46",
      "name" : "Aero II"
    },
    "133" : {
      "classCategory" : "53",
      "icon" : "000409.png",
      "id" : "133",
      "job" : "conjurer",
      "levelReq" : "50",
      "name" : "Medica II"
    },
    "134" : {
      "classCategory" : "53",
      "icon" : "000416.png",
      "id" : "134",
      "job" : "conjurer",
      "levelReq" : "15",
      "name" : "Fluid Aura"
    },
    "135" : {
      "classCategory" : "53",
      "icon" : "000406.png",
      "id" : "135",
      "job" : "conjurer",
      "levelReq" : "30",
      "name" : "Cure II"
    },
    "136" : {
      "classCategory" : "25",
      "icon" : "002626.png",
      "id" : "136",
      "job" : "white_mage",
      "levelReq" : "30",
      "name" : "Presence of Mind"
    },
    "137" : {
      "classCategory" : "25",
      "icon" : "002628.png",
      "id" : "137",
      "job" : "white_mage",
      "levelReq" : "35",
      "name" : "Regen"
    },
    "139" : {
      "classCategory" : "25",
      "icon" : "002629.png",
      "id" : "139",
      "job" : "white_mage",
      "levelReq" : "45",
      "name" : "Holy"
    },
    "140" : {
      "classCategory" : "25",
      "icon" : "002627.png",
      "id" : "140",
      "job" : "white_mage",
      "levelReq" : "50",
      "name" : "Benediction"
    },
    "141" : {
      "classCategory" : "55",
      "icon" : "000451.png",
      "id" : "141",
      "job" : "thaumaturge",
      "levelReq" : "2",
      "name" : "Fire"
    },
    "142" : {
      "classCategory" : "55",
      "icon" : "000454.png",
      "id" : "142",
      "job" : "thaumaturge",
      "levelReq" : "1",
      "name" : "Blizzard"
    },
    "144" : {
      "classCategory" : "55",
      "icon" : "000457.png",
      "id" : "144",
      "job" : "thaumaturge",
      "levelReq" : "6",
      "name" : "Thunder"
    },
    "145" : {
      "classCategory" : "55",
      "icon" : "000465.png",
      "id" : "145",
      "job" : "thaumaturge",
      "levelReq" : "10",
      "name" : "Sleep"
    },
    "146" : {
      "classCategory" : "55",
      "icon" : "000455.png",
      "id" : "146",
      "job" : "thaumaturge",
      "levelReq" : "12",
      "name" : "Blizzard II"
    },
    "147" : {
      "classCategory" : "55",
      "icon" : "000452.png",
      "id" : "147",
      "job" : "thaumaturge",
      "levelReq" : "18",
      "name" : "Fire II"
    },
    "149" : {
      "classCategory" : "55",
      "icon" : "000466.png",
      "id" : "149",
      "job" : "thaumaturge",
      "levelReq" : "4",
      "name" : "Transpose"
    },
    "152" : {
      "classCategory" : "55",
      "icon" : "000453.png",
      "id" : "152",
      "job" : "thaumaturge",
      "levelReq" : "34",
      "name" : "Fire III"
    },
    "153" : {
      "classCategory" : "26",
      "icon" : "000459.png",
      "id" : "153",
      "job" : "black_mage",
      "levelReq" : "45",
      "name" : "Thunder III"
    },
    "154" : {
      "classCategory" : "26",
      "icon" : "000456.png",
      "id" : "154",
      "job" : "black_mage",
      "levelReq" : "40",
      "name" : "Blizzard III"
    },
    "155" : {
      "classCategory" : "55",
      "icon" : "000467.png",
      "id" : "155",
      "job" : "thaumaturge",
      "levelReq" : "50",
      "name" : "Aetherial Manipulation"
    },
    "156" : {
      "classCategory" : "55",
      "icon" : "000462.png",
      "id" : "156",
      "job" : "thaumaturge",
      "levelReq" : "15",
      "name" : "Scathe"
    },
    "157" : {
      "classCategory" : "55",
      "icon" : "000463.png",
      "id" : "157",
      "job" : "thaumaturge",
      "levelReq" : "30",
      "name" : "Manaward"
    },
    "158" : {
      "classCategory" : "26",
      "icon" : "002651.png",
      "id" : "158",
      "job" : "black_mage",
      "levelReq" : "30",
      "name" : "Convert"
    },
    "159" : {
      "classCategory" : "26",
      "icon" : "002653.png",
      "id" : "159",
      "job" : "black_mage",
      "levelReq" : "35",
      "name" : "Freeze"
    },
    "162" : {
      "classCategory" : "26",
      "icon" : "002652.png",
      "id" : "162",
      "job" : "black_mage",
      "levelReq" : "50",
      "name" : "Flare"
    },
    "163" : {
      "classCategory" : "68",
      "icon" : "000501.png",
      "id" : "163",
      "job" : "arcanist",
      "levelReq" : "1",
      "name" : "Ruin"
    },
    "164" : {
      "classCategory" : "68",
      "icon" : "000503.png",
      "id" : "164",
      "job" : "arcanist",
      "levelReq" : "2",
      "name" : "Bio"
    },
    "165" : {
      "classCategory" : "68",
      "icon" : "000516.png",
      "id" : "165",
      "job" : "arcanist",
      "levelReq" : "4",
      "name" : "Summon"
    },
    "166" : {
      "classCategory" : "68",
      "icon" : "000510.png",
      "id" : "166",
      "job" : "arcanist",
      "levelReq" : "6",
      "name" : "Aetherflow"
    },
    "167" : {
      "classCategory" : "68",
      "icon" : "000514.png",
      "id" : "167",
      "job" : "arcanist",
      "levelReq" : "6",
      "name" : "Energy Drain"
    },
    "168" : {
      "classCategory" : "68",
      "icon" : "000505.png",
      "id" : "168",
      "job" : "arcanist",
      "levelReq" : "10",
      "name" : "Miasma"
    },
    "170" : {
      "classCategory" : "68",
      "icon" : "000517.png",
      "id" : "170",
      "job" : "arcanist",
      "levelReq" : "15",
      "name" : "Summon II"
    },
    "172" : {
      "classCategory" : "68",
      "icon" : "000502.png",
      "id" : "172",
      "job" : "arcanist",
      "levelReq" : "38",
      "name" : "Ruin II"
    },
    "173" : {
      "classCategory" : "68",
      "icon" : "000511.png",
      "id" : "173",
      "job" : "arcanist",
      "levelReq" : "18",
      "name" : "Resurrection"
    },
    "174" : {
      "classCategory" : "68",
      "icon" : "000507.png",
      "id" : "174",
      "job" : "arcanist",
      "levelReq" : "30",
      "name" : "Bane"
    },
    "176" : {
      "classCategory" : "68",
      "icon" : "000509.png",
      "id" : "176",
      "job" : "arcanist",
      "levelReq" : "42",
      "name" : "Rouse"
    },
    "178" : {
      "classCategory" : "68",
      "icon" : "000504.png",
      "id" : "178",
      "job" : "arcanist",
      "levelReq" : "26",
      "name" : "Bio II"
    },
    "179" : {
      "classCategory" : "68",
      "icon" : "000515.png",
      "id" : "179",
      "job" : "arcanist",
      "levelReq" : "50",
      "name" : "Shadow Flare"
    },
    "180" : {
      "classCategory" : "28",
      "icon" : "002680.png",
      "id" : "180",
      "job" : "summoner",
      "levelReq" : "30",
      "name" : "Summon III"
    },
    "181" : {
      "classCategory" : "28",
      "icon" : "002676.png",
      "id" : "181",
      "job" : "summoner",
      "levelReq" : "35",
      "name" : "Fester"
    },
    "182" : {
      "classCategory" : "28",
      "icon" : "002678.png",
      "id" : "182",
      "job" : "summoner",
      "levelReq" : "40",
      "name" : "Tri-bind"
    },
    "184" : {
      "classCategory" : "28",
      "icon" : "002677.png",
      "id" : "184",
      "job" : "summoner",
      "levelReq" : "50",
      "name" : "Enkindle"
    },
    "185" : {
      "classCategory" : "29",
      "icon" : "002801.png",
      "id" : "185",
      "job" : "scholar",
      "levelReq" : "30",
      "name" : "Adloquium"
    },
    "186" : {
      "classCategory" : "29",
      "icon" : "002802.png",
      "id" : "186",
      "job" : "scholar",
      "levelReq" : "35",
      "name" : "Succor"
    },
    "188" : {
      "classCategory" : "29",
      "icon" : "002804.png",
      "id" : "188",
      "job" : "scholar",
      "levelReq" : "45",
      "name" : "Sacred Soil"
    },
    "189" : {
      "classCategory" : "29",
      "icon" : "002805.png",
      "id" : "189",
      "job" : "scholar",
      "levelReq" : "50",
      "name" : "Lustrate"
    },
    "190" : {
      "classCategory" : "68",
      "icon" : "000518.png",
      "id" : "190",
      "job" : "arcanist",
      "levelReq" : "4",
      "name" : "Physick"
    },
    "787" : {
      "classCategory" : "28",
      "icon" : "002701.png",
      "id" : "787",
      "job" : "titan-egi",
      "levelReq" : "1",
      "name" : "Rock Buster"
    },
    "788" : {
      "classCategory" : "28",
      "icon" : "002702.png",
      "id" : "788",
      "job" : "titan-egi",
      "levelReq" : "1",
      "name" : "Mountain Buster"
    },
    "789" : {
      "classCategory" : "28",
      "icon" : "002703.png",
      "id" : "789",
      "job" : "titan-egi",
      "levelReq" : "20",
      "name" : "Earthen Ward"
    },
    "790" : {
      "classCategory" : "28",
      "icon" : "002704.png",
      "id" : "790",
      "job" : "titan-egi",
      "levelReq" : "40",
      "name" : "Landslide"
    },
    "791" : {
      "classCategory" : "28",
      "icon" : "002705.png",
      "id" : "791",
      "job" : "titan-egi",
      "levelReq" : "50",
      "name" : "Earthen Fury"
    },
    "792" : {
      "classCategory" : "28",
      "icon" : "002711.png",
      "id" : "792",
      "job" : "garuda-egi",
      "levelReq" : "1",
      "name" : "Wind Blade"
    },
    "793" : {
      "classCategory" : "28",
      "icon" : "002713.png",
      "id" : "793",
      "job" : "garuda-egi",
      "levelReq" : "1",
      "name" : "Shockwave"
    },
    "794" : {
      "classCategory" : "28",
      "icon" : "002712.png",
      "id" : "794",
      "job" : "garuda-egi",
      "levelReq" : "20",
      "name" : "Aerial Slash"
    },
    "795" : {
      "classCategory" : "28",
      "icon" : "002714.png",
      "id" : "795",
      "job" : "garuda-egi",
      "levelReq" : "40",
      "name" : "Contagion"
    },
    "796" : {
      "classCategory" : "28",
      "icon" : "002715.png",
      "id" : "796",
      "job" : "garuda-egi",
      "levelReq" : "50",
      "name" : "Aerial Blast"
    },
    "797" : {
      "classCategory" : "28",
      "icon" : "002721.png",
      "id" : "797",
      "job" : "ifrit-egi",
      "levelReq" : "1",
      "name" : "Crimson Cyclone"
    },
    "798" : {
      "classCategory" : "28",
      "icon" : "002722.png",
      "id" : "798",
      "job" : "ifrit-egi",
      "levelReq" : "1",
      "name" : "Burning Strike"
    },
    "799" : {
      "classCategory" : "28",
      "icon" : "002723.png",
      "id" : "799",
      "job" : "ifrit-egi",
      "levelReq" : "20",
      "name" : "Radiant Shield"
    },
    "800" : {
      "classCategory" : "28",
      "icon" : "002724.png",
      "id" : "800",
      "job" : "ifrit-egi",
      "levelReq" : "40",
      "name" : "Flaming Crush"
    },
    "801" : {
      "classCategory" : "28",
      "icon" : "002725.png",
      "id" : "801",
      "job" : "ifrit-egi",
      "levelReq" : "50",
      "name" : "Inferno"
    },
    "802" : {
      "classCategory" : "29",
      "icon" : "002826.png",
      "id" : "802",
      "job" : "eos",
      "levelReq" : "1",
      "name" : "Embrace"
    },
    "803" : {
      "classCategory" : "29",
      "icon" : "002827.png",
      "id" : "803",
      "job" : "eos",
      "levelReq" : "1",
      "name" : "Whispering Dawn"
    },
    "804" : {
      "classCategory" : "29",
      "icon" : "002828.png",
      "id" : "804",
      "job" : "eos",
      "levelReq" : "20",
      "name" : "Fey Covenant"
    },
    "805" : {
      "classCategory" : "29",
      "icon" : "002829.png",
      "id" : "805",
      "job" : "eos",
      "levelReq" : "40",
      "name" : "Fey Illumination"
    },
    "806" : {
      "classCategory" : "29",
      "icon" : "002836.png",
      "id" : "806",
      "job" : "selene",
      "levelReq" : "1",
      "name" : "Embrace"
    },
    "807" : {
      "classCategory" : "29",
      "icon" : "002837.png",
      "id" : "807",
      "job" : "selene",
      "levelReq" : "1",
      "name" : "Silent Dusk"
    },
    "808" : {
      "classCategory" : "29",
      "icon" : "002838.png",
      "id" : "808",
      "job" : "selene",
      "levelReq" : "20",
      "name" : "Fey Glow"
    },
    "809" : {
      "classCategory" : "29",
      "icon" : "002839.png",
      "id" : "809",
      "job" : "selene",
      "levelReq" : "40",
      "name" : "Fey Light"
    },
    "810" : {
      "classCategory" : "29",
      "icon" : "002811.png",
      "id" : "810",
      "job" : "selene",
      "levelReq" : "20",
      "name" : "Fey Caress"
    },
    "811" : {
      "classCategory" : "29",
      "icon" : "002812.png",
      "id" : "811",
      "job" : "selene",
      "levelReq" : "40",
      "name" : "Fey Wind"
    },
    "2240" : {
      "classCategory" : "93",
      "icon" : "000601.png",
      "id" : "2240",
      "job" : "rogue",
      "levelReq" : "1",
      "name" : "Spinning Edge"
    },
    "2241" : {
      "classCategory" : "93",
      "icon" : "000607.png",
      "id" : "2241",
      "job" : "rogue",
      "levelReq" : "2",
      "name" : "Shade Shift"
    },
    "2242" : {
      "classCategory" : "93",
      "icon" : "000602.png",
      "id" : "2242",
      "job" : "rogue",
      "levelReq" : "4",
      "name" : "Gust Slash"
    },
    "2245" : {
      "classCategory" : "93",
      "icon" : "000609.png",
      "id" : "2245",
      "job" : "rogue",
      "levelReq" : "10",
      "name" : "Hide"
    },
    "2246" : {
      "classCategory" : "93",
      "icon" : "000612.png",
      "id" : "2246",
      "job" : "rogue",
      "levelReq" : "12",
      "name" : "Assassinate"
    },
    "2247" : {
      "classCategory" : "93",
      "icon" : "000614.png",
      "id" : "2247",
      "job" : "rogue",
      "levelReq" : "15",
      "name" : "Throwing Dagger"
    },
    "2248" : {
      "classCategory" : "93",
      "icon" : "000613.png",
      "id" : "2248",
      "job" : "rogue",
      "levelReq" : "15",
      "name" : "Mug"
    },
    "2253" : {
      "classCategory" : "93",
      "icon" : "000609.png",
      "id" : "2253",
      "job" : "rogue",
      "levelReq" : "0",
      "name" : "Hide"
    },
    "2254" : {
      "classCategory" : "93",
      "icon" : "000615.png",
      "id" : "2254",
      "job" : "rogue",
      "levelReq" : "42",
      "name" : "Death Blossom"
    },
    "2255" : {
      "classCategory" : "93",
      "icon" : "000605.png",
      "id" : "2255",
      "job" : "rogue",
      "levelReq" : "26",
      "name" : "Aeolian Edge"
    },
    "2256" : {
      "classCategory" : "93",
      "icon" : "000616.png",
      "id" : "2256",
      "job" : "rogue",
      "levelReq" : "30",
      "name" : "Jugulate"
    },
    "2257" : {
      "classCategory" : "93",
      "icon" : "000606.png",
      "id" : "2257",
      "job" : "rogue",
      "levelReq" : "38",
      "name" : "Shadow Fang"
    },
    "2258" : {
      "classCategory" : "93",
      "icon" : "000618.png",
      "id" : "2258",
      "job" : "rogue",
      "levelReq" : "18",
      "name" : "Trick Attack"
    },
    "2259" : {
      "classCategory" : "92",
      "icon" : "002901.png",
      "id" : "2259",
      "job" : "ninja",
      "levelReq" : "30",
      "name" : "Ten"
    },
    "2260" : {
      "classCategory" : "92",
      "icon" : "002904.png",
      "id" : "2260",
      "job" : "ninja",
      "levelReq" : "30",
      "name" : "Ninjutsu"
    },
    "2261" : {
      "classCategory" : "92",
      "icon" : "002902.png",
      "id" : "2261",
      "job" : "ninja",
      "levelReq" : "35",
      "name" : "Chi"
    },
    "2262" : {
      "classCategory" : "92",
      "icon" : "002905.png",
      "id" : "2262",
      "job" : "ninja",
      "levelReq" : "40",
      "name" : "Shukuchi"
    },
    "2263" : {
      "classCategory" : "92",
      "icon" : "002903.png",
      "id" : "2263",
      "job" : "ninja",
      "levelReq" : "45",
      "name" : "Jin"
    },
    "2264" : {
      "classCategory" : "92",
      "icon" : "002906.png",
      "id" : "2264",
      "job" : "ninja",
      "levelReq" : "50",
      "name" : "Kassatsu"
    },
    "2864" : {
      "classCategory" : "96",
      "icon" : "003026.png",
      "id" : "2864",
      "job" : "machinist",
      "levelReq" : "40",
      "name" : "Rook Autoturret"
    },
    "2865" : {
      "classCategory" : "96",
      "icon" : "003027.png",
      "id" : "2865",
      "job" : "machinist",
      "levelReq" : "50",
      "name" : "Bishop Autoturret"
    },
    "2866" : {
      "classCategory" : "96",
      "icon" : "003001.png",
      "id" : "2866",
      "job" : "machinist",
      "levelReq" : "1",
      "name" : "Split Shot"
    },
    "2867" : {
      "classCategory" : "96",
      "icon" : "003019.png",
      "id" : "2867",
      "job" : "machinist",
      "levelReq" : "4",
      "name" : "Reload"
    },
    "2868" : {
      "classCategory" : "96",
      "icon" : "003002.png",
      "id" : "2868",
      "job" : "machinist",
      "levelReq" : "2",
      "name" : "Slug Shot"
    },
    "2870" : {
      "classCategory" : "96",
      "icon" : "003014.png",
      "id" : "2870",
      "job" : "machinist",
      "levelReq" : "18",
      "name" : "Spread Shot"
    },
    "2872" : {
      "classCategory" : "96",
      "icon" : "003003.png",
      "id" : "2872",
      "job" : "machinist",
      "levelReq" : "30",
      "name" : "Hot Shot"
    },
    "2873" : {
      "classCategory" : "96",
      "icon" : "003004.png",
      "id" : "2873",
      "job" : "machinist",
      "levelReq" : "35",
      "name" : "Clean Shot"
    },
    "2874" : {
      "classCategory" : "96",
      "icon" : "003005.png",
      "id" : "2874",
      "job" : "machinist",
      "levelReq" : "54",
      "name" : "Gauss Round"
    },
    "2875" : {
      "classCategory" : "96",
      "icon" : "003007.png",
      "id" : "2875",
      "job" : "machinist",
      "levelReq" : "6",
      "name" : "Heartbreak"
    },
    "2876" : {
      "classCategory" : "96",
      "icon" : "003022.png",
      "id" : "2876",
      "job" : "machinist",
      "levelReq" : "10",
      "name" : "Reassemble"
    },
    "2878" : {
      "classCategory" : "96",
      "icon" : "003018.png",
      "id" : "2878",
      "job" : "machinist",
      "levelReq" : "38",
      "name" : "Wildfire"
    },
    "2879" : {
      "classCategory" : "96",
      "icon" : "003020.png",
      "id" : "2879",
      "job" : "machinist",
      "levelReq" : "26",
      "name" : "Quick Reload"
    },
    "2880" : {
      "classCategory" : "96",
      "icon" : "003021.png",
      "id" : "2880",
      "job" : "machinist",
      "levelReq" : "52",
      "name" : "Gauss Barrel"
    },
    "2881" : {
      "classCategory" : "96",
      "icon" : "003023.png",
      "id" : "2881",
      "job" : "machinist",
      "levelReq" : "30",
      "name" : "Rapid Fire"
    },
    "2885" : {
      "classCategory" : "96",
      "icon" : "003024.png",
      "id" : "2885",
      "job" : "machinist",
      "levelReq" : "58",
      "name" : "Hypercharge"
    },
    "2887" : {
      "classCategory" : "96",
      "icon" : "003011.png",
      "id" : "2887",
      "job" : "machinist",
      "levelReq" : "56",
      "name" : "Dismantle"
    },
    "2888" : {
      "classCategory" : "96",
      "icon" : "003016.png",
      "id" : "2888",
      "job" : "machinist",
      "levelReq" : "15",
      "name" : "Blank"
    },
    "2890" : {
      "classCategory" : "96",
      "icon" : "003017.png",
      "id" : "2890",
      "job" : "machinist",
      "levelReq" : "60",
      "name" : "Ricochet"
    },
    "3487" : {
      "classCategory" : "96",
      "icon" : "003028.png",
      "id" : "3487",
      "job" : "machinist",
      "levelReq" : "40",
      "name" : "Turret Retrieval"
    },
    "3538" : {
      "classCategory" : "20",
      "icon" : "002506.png",
      "id" : "3538",
      "job" : "paladin",
      "levelReq" : "54",
      "name" : "Goring Blade"
    },
    "3539" : {
      "classCategory" : "20",
      "icon" : "002507.png",
      "id" : "3539",
      "job" : "paladin",
      "levelReq" : "60",
      "name" : "Royal Authority"
    },
    "3540" : {
      "classCategory" : "20",
      "icon" : "002508.png",
      "id" : "3540",
      "job" : "paladin",
      "levelReq" : "56",
      "name" : "Divine Veil"
    },
    "3541" : {
      "classCategory" : "20",
      "icon" : "002509.png",
      "id" : "3541",
      "job" : "paladin",
      "levelReq" : "58",
      "name" : "Clemency"
    },
    "3542" : {
      "classCategory" : "20",
      "icon" : "002510.png",
      "id" : "3542",
      "job" : "paladin",
      "levelReq" : "52",
      "name" : "Sheltron"
    },
    "3543" : {
      "classCategory" : "21",
      "icon" : "002531.png",
      "id" : "3543",
      "job" : "monk",
      "levelReq" : "60",
      "name" : "Tornado Kick"
    },
    "3544" : {
      "classCategory" : "21",
      "icon" : "002532.png",
      "id" : "3544",
      "job" : "monk",
      "levelReq" : "58",
      "name" : "Purification"
    },
    "3545" : {
      "classCategory" : "21",
      "icon" : "002533.png",
      "id" : "3545",
      "job" : "monk",
      "levelReq" : "56",
      "name" : "Elixir Field"
    },
    "3546" : {
      "classCategory" : "21",
      "icon" : "002534.png",
      "id" : "3546",
      "job" : "monk",
      "levelReq" : "54",
      "name" : "Meditation"
    },
    "3548" : {
      "classCategory" : "22",
      "icon" : "002556.png",
      "id" : "3548",
      "job" : "warrior",
      "levelReq" : "52",
      "name" : "Deliverance"
    },
    "3549" : {
      "classCategory" : "22",
      "icon" : "002557.png",
      "id" : "3549",
      "job" : "warrior",
      "levelReq" : "54",
      "name" : "Fell Cleave"
    },
    "3550" : {
      "classCategory" : "22",
      "icon" : "002558.png",
      "id" : "3550",
      "job" : "warrior",
      "levelReq" : "60",
      "name" : "Decimate"
    },
    "3551" : {
      "classCategory" : "22",
      "icon" : "002559.png",
      "id" : "3551",
      "job" : "warrior",
      "levelReq" : "56",
      "name" : "Raw Intuition"
    },
    "3552" : {
      "classCategory" : "22",
      "icon" : "002560.png",
      "id" : "3552",
      "job" : "warrior",
      "levelReq" : "58",
      "name" : "Equilibrium"
    },
    "3553" : {
      "classCategory" : "23",
      "icon" : "002581.png",
      "id" : "3553",
      "job" : "dragoon",
      "levelReq" : "54",
      "name" : "Blood of the Dragon"
    },
    "3554" : {
      "classCategory" : "23",
      "icon" : "002582.png",
      "id" : "3554",
      "job" : "dragoon",
      "levelReq" : "56",
      "name" : "Fang and Claw"
    },
    "3555" : {
      "classCategory" : "23",
      "icon" : "002583.png",
      "id" : "3555",
      "job" : "dragoon",
      "levelReq" : "60",
      "name" : "Geirskogul"
    },
    "3556" : {
      "classCategory" : "23",
      "icon" : "002584.png",
      "id" : "3556",
      "job" : "dragoon",
      "levelReq" : "58",
      "name" : "Wheeling Thrust"
    },
    "3557" : {
      "classCategory" : "23",
      "icon" : "002585.png",
      "id" : "3557",
      "job" : "dragoon",
      "levelReq" : "52",
      "name" : "Battle Litany"
    },
    "3558" : {
      "classCategory" : "24",
      "icon" : "002606.png",
      "id" : "3558",
      "job" : "bard",
      "levelReq" : "54",
      "name" : "Empyreal Arrow"
    },
    "3559" : {
      "classCategory" : "24",
      "icon" : "002607.png",
      "id" : "3559",
      "job" : "bard",
      "levelReq" : "52",
      "name" : "the Wanderer's Minuet"
    },
    "3560" : {
      "classCategory" : "24",
      "icon" : "002608.png",
      "id" : "3560",
      "job" : "bard",
      "levelReq" : "56",
      "name" : "Iron Jaws"
    },
    "3561" : {
      "classCategory" : "24",
      "icon" : "002609.png",
      "id" : "3561",
      "job" : "bard",
      "levelReq" : "58",
      "name" : "the Warden's Paean"
    },
    "3562" : {
      "classCategory" : "24",
      "icon" : "002610.png",
      "id" : "3562",
      "job" : "bard",
      "levelReq" : "60",
      "name" : "Sidewinder"
    },
    "3563" : {
      "classCategory" : "92",
      "icon" : "002915.png",
      "id" : "3563",
      "job" : "ninja",
      "levelReq" : "54",
      "name" : "Armor Crush"
    },
    "3564" : {
      "classCategory" : "92",
      "icon" : "002916.png",
      "id" : "3564",
      "job" : "ninja",
      "levelReq" : "56",
      "name" : "Shadewalker"
    },
    "3565" : {
      "classCategory" : "92",
      "icon" : "002917.png",
      "id" : "3565",
      "job" : "ninja",
      "levelReq" : "52",
      "name" : "Smoke Screen"
    },
    "3566" : {
      "classCategory" : "92",
      "icon" : "002918.png",
      "id" : "3566",
      "job" : "ninja",
      "levelReq" : "60",
      "name" : "Dream Within a Dream"
    },
    "3567" : {
      "classCategory" : "92",
      "icon" : "002919.png",
      "id" : "3567",
      "job" : "ninja",
      "levelReq" : "58",
      "name" : "Duality"
    },
    "3568" : {
      "classCategory" : "25",
      "icon" : "002631.png",
      "id" : "3568",
      "job" : "white_mage",
      "levelReq" : "54",
      "name" : "Stone III"
    },
    "3569" : {
      "classCategory" : "25",
      "icon" : "002632.png",
      "id" : "3569",
      "job" : "white_mage",
      "levelReq" : "52",
      "name" : "Asylum"
    },
    "3570" : {
      "classCategory" : "25",
      "icon" : "002633.png",
      "id" : "3570",
      "job" : "white_mage",
      "levelReq" : "60",
      "name" : "Tetragrammaton"
    },
    "3571" : {
      "classCategory" : "25",
      "icon" : "002634.png",
      "id" : "3571",
      "job" : "white_mage",
      "levelReq" : "56",
      "name" : "Assize"
    },
    "3572" : {
      "classCategory" : "25",
      "icon" : "002635.png",
      "id" : "3572",
      "job" : "white_mage",
      "levelReq" : "58",
      "name" : "Aero III"
    },
    "3573" : {
      "classCategory" : "26",
      "icon" : "002656.png",
      "id" : "3573",
      "job" : "black_mage",
      "levelReq" : "52",
      "name" : "Ley Lines"
    },
    "3574" : {
      "classCategory" : "26",
      "icon" : "002657.png",
      "id" : "3574",
      "job" : "black_mage",
      "levelReq" : "54",
      "name" : "Sharpcast"
    },
    "3575" : {
      "classCategory" : "26",
      "icon" : "002658.png",
      "id" : "3575",
      "job" : "black_mage",
      "levelReq" : "56",
      "name" : "Enochian"
    },
    "3576" : {
      "classCategory" : "26",
      "icon" : "002659.png",
      "id" : "3576",
      "job" : "black_mage",
      "levelReq" : "58",
      "name" : "Blizzard IV"
    },
    "3577" : {
      "classCategory" : "26",
      "icon" : "002660.png",
      "id" : "3577",
      "job" : "black_mage",
      "levelReq" : "60",
      "name" : "Fire IV"
    },
    "3578" : {
      "classCategory" : "28",
      "icon" : "002681.png",
      "id" : "3578",
      "job" : "summoner",
      "levelReq" : "52",
      "name" : "Painflare"
    },
    "3579" : {
      "classCategory" : "28",
      "icon" : "002682.png",
      "id" : "3579",
      "job" : "summoner",
      "levelReq" : "54",
      "name" : "Ruin III"
    },
    "3580" : {
      "classCategory" : "28",
      "icon" : "002683.png",
      "id" : "3580",
      "job" : "summoner",
      "levelReq" : "56",
      "name" : "Tri-disaster"
    },
    "3581" : {
      "classCategory" : "28",
      "icon" : "002684.png",
      "id" : "3581",
      "job" : "summoner",
      "levelReq" : "58",
      "name" : "Dreadwyrm Trance"
    },
    "3582" : {
      "classCategory" : "28",
      "icon" : "002685.png",
      "id" : "3582",
      "job" : "summoner",
      "levelReq" : "60",
      "name" : "Deathflare"
    },
    "3583" : {
      "classCategory" : "29",
      "icon" : "002806.png",
      "id" : "3583",
      "job" : "scholar",
      "levelReq" : "52",
      "name" : "Indomitability"
    },
    "3584" : {
      "classCategory" : "29",
      "icon" : "002807.png",
      "id" : "3584",
      "job" : "scholar",
      "levelReq" : "54",
      "name" : "Broil"
    },
    "3585" : {
      "classCategory" : "29",
      "icon" : "002808.png",
      "id" : "3585",
      "job" : "scholar",
      "levelReq" : "56",
      "name" : "Deployment Tactics"
    },
    "3586" : {
      "classCategory" : "29",
      "icon" : "002809.png",
      "id" : "3586",
      "job" : "scholar",
      "levelReq" : "58",
      "name" : "Emergency Tactics"
    },
    "3587" : {
      "classCategory" : "29",
      "icon" : "002810.png",
      "id" : "3587",
      "job" : "scholar",
      "levelReq" : "60",
      "name" : "Dissipation"
    },
    "3590" : {
      "classCategory" : "99",
      "icon" : "003101.png",
      "id" : "3590",
      "job" : "astrologian",
      "levelReq" : "30",
      "name" : "Draw"
    },
    "3591" : {
      "classCategory" : "99",
      "icon" : "003103.png",
      "id" : "3591",
      "job" : "astrologian",
      "levelReq" : "35",
      "name" : "Royal Road"
    },
    "3592" : {
      "classCategory" : "99",
      "icon" : "003104.png",
      "id" : "3592",
      "job" : "astrologian",
      "levelReq" : "40",
      "name" : "Spread"
    },
    "3593" : {
      "classCategory" : "99",
      "icon" : "003105.png",
      "id" : "3593",
      "job" : "astrologian",
      "levelReq" : "45",
      "name" : "Redraw"
    },
    "3594" : {
      "classCategory" : "99",
      "icon" : "003126.png",
      "id" : "3594",
      "job" : "astrologian",
      "levelReq" : "2",
      "name" : "Benefic"
    },
    "3595" : {
      "classCategory" : "99",
      "icon" : "003127.png",
      "id" : "3595",
      "job" : "astrologian",
      "levelReq" : "34",
      "name" : "Aspected Benefic"
    },
    "3596" : {
      "classCategory" : "99",
      "icon" : "003120.png",
      "id" : "3596",
      "job" : "astrologian",
      "levelReq" : "1",
      "name" : "Malefic"
    },
    "3598" : {
      "classCategory" : "99",
      "icon" : "003122.png",
      "id" : "3598",
      "job" : "astrologian",
      "levelReq" : "54",
      "name" : "Malefic II"
    },
    "3599" : {
      "classCategory" : "99",
      "icon" : "003124.png",
      "id" : "3599",
      "job" : "astrologian",
      "levelReq" : "4",
      "name" : "Combust"
    },
    "3600" : {
      "classCategory" : "99",
      "icon" : "003129.png",
      "id" : "3600",
      "job" : "astrologian",
      "levelReq" : "10",
      "name" : "Helios"
    },
    "3601" : {
      "classCategory" : "99",
      "icon" : "003130.png",
      "id" : "3601",
      "job" : "astrologian",
      "levelReq" : "42",
      "name" : "Aspected Helios"
    },
    "3603" : {
      "classCategory" : "99",
      "icon" : "003132.png",
      "id" : "3603",
      "job" : "astrologian",
      "levelReq" : "12",
      "name" : "Ascend"
    },
    "3604" : {
      "classCategory" : "99",
      "icon" : "003133.png",
      "id" : "3604",
      "job" : "astrologian",
      "levelReq" : "30",
      "name" : "Diurnal Sect"
    },
    "3605" : {
      "classCategory" : "99",
      "icon" : "003134.png",
      "id" : "3605",
      "job" : "astrologian",
      "levelReq" : "50",
      "name" : "Nocturnal Sect"
    },
    "3606" : {
      "classCategory" : "99",
      "icon" : "003135.png",
      "id" : "3606",
      "job" : "astrologian",
      "levelReq" : "6",
      "name" : "Lightspeed"
    },
    "3608" : {
      "classCategory" : "99",
      "icon" : "003125.png",
      "id" : "3608",
      "job" : "astrologian",
      "levelReq" : "46",
      "name" : "Combust II"
    },
    "3610" : {
      "classCategory" : "99",
      "icon" : "003128.png",
      "id" : "3610",
      "job" : "astrologian",
      "levelReq" : "26",
      "name" : "Benefic II"
    },
    "3611" : {
      "classCategory" : "99",
      "icon" : "003138.png",
      "id" : "3611",
      "job" : "astrologian",
      "levelReq" : "56",
      "name" : "Time Dilation"
    },
    "3612" : {
      "classCategory" : "99",
      "icon" : "003139.png",
      "id" : "3612",
      "job" : "astrologian",
      "levelReq" : "50",
      "name" : "Synastry"
    },
    "3613" : {
      "classCategory" : "99",
      "icon" : "003140.png",
      "id" : "3613",
      "job" : "astrologian",
      "levelReq" : "58",
      "name" : "Collective Unconscious"
    },
    "3614" : {
      "classCategory" : "99",
      "icon" : "003141.png",
      "id" : "3614",
      "job" : "astrologian",
      "levelReq" : "15",
      "name" : "Essential Dignity"
    },
    "3615" : {
      "classCategory" : "99",
      "icon" : "003123.png",
      "id" : "3615",
      "job" : "astrologian",
      "levelReq" : "52",
      "name" : "Gravity"
    },
    "3616" : {
      "classCategory" : "99",
      "icon" : "003142.png",
      "id" : "3616",
      "job" : "astrologian",
      "levelReq" : "60",
      "name" : "Celestial Opposition"
    },
    "3617" : {
      "classCategory" : "98",
      "icon" : "003051.png",
      "id" : "3617",
      "job" : "dark_knight",
      "levelReq" : "1",
      "name" : "Hard Slash"
    },
    "3619" : {
      "classCategory" : "98",
      "icon" : "003052.png",
      "id" : "3619",
      "job" : "dark_knight",
      "levelReq" : "4",
      "name" : "Spinning Slash"
    },
    "3621" : {
      "classCategory" : "98",
      "icon" : "003063.png",
      "id" : "3621",
      "job" : "dark_knight",
      "levelReq" : "6",
      "name" : "Unleash"
    },
    "3623" : {
      "classCategory" : "98",
      "icon" : "003054.png",
      "id" : "3623",
      "job" : "dark_knight",
      "levelReq" : "10",
      "name" : "Syphon Strike"
    },
    "3624" : {
      "classCategory" : "98",
      "icon" : "003062.png",
      "id" : "3624",
      "job" : "dark_knight",
      "levelReq" : "15",
      "name" : "Unmend"
    },
    "3625" : {
      "classCategory" : "98",
      "icon" : "003071.png",
      "id" : "3625",
      "job" : "dark_knight",
      "levelReq" : "18",
      "name" : "Blood Weapon"
    },
    "3627" : {
      "classCategory" : "98",
      "icon" : "003053.png",
      "id" : "3627",
      "job" : "dark_knight",
      "levelReq" : "26",
      "name" : "Power Slash"
    },
    "3628" : {
      "classCategory" : "98",
      "icon" : "003068.png",
      "id" : "3628",
      "job" : "dark_knight",
      "levelReq" : "30",
      "name" : "Darkside"
    },
    "3629" : {
      "classCategory" : "98",
      "icon" : "003070.png",
      "id" : "3629",
      "job" : "dark_knight",
      "levelReq" : "30",
      "name" : "Grit"
    },
    "3631" : {
      "classCategory" : "98",
      "icon" : "003072.png",
      "id" : "3631",
      "job" : "dark_knight",
      "levelReq" : "35",
      "name" : "Blood Price"
    },
    "3632" : {
      "classCategory" : "98",
      "icon" : "003055.png",
      "id" : "3632",
      "job" : "dark_knight",
      "levelReq" : "38",
      "name" : "Souleater"
    },
    "3633" : {
      "classCategory" : "98",
      "icon" : "003065.png",
      "id" : "3633",
      "job" : "dark_knight",
      "levelReq" : "40",
      "name" : "Dark Passenger"
    },
    "3634" : {
      "classCategory" : "98",
      "icon" : "003076.png",
      "id" : "3634",
      "job" : "dark_knight",
      "levelReq" : "42",
      "name" : "Dark Mind"
    },
    "3635" : {
      "classCategory" : "98",
      "icon" : "003069.png",
      "id" : "3635",
      "job" : "dark_knight",
      "levelReq" : "45",
      "name" : "Dark Arts"
    },
    "3636" : {
      "classCategory" : "98",
      "icon" : "003075.png",
      "id" : "3636",
      "job" : "dark_knight",
      "levelReq" : "46",
      "name" : "Shadow Wall"
    },
    "3638" : {
      "classCategory" : "98",
      "icon" : "003077.png",
      "id" : "3638",
      "job" : "dark_knight",
      "levelReq" : "50",
      "name" : "Living Dead"
    },
    "3639" : {
      "classCategory" : "98",
      "icon" : "003066.png",
      "id" : "3639",
      "job" : "dark_knight",
      "levelReq" : "52",
      "name" : "Salted Earth"
    },
    "3640" : {
      "classCategory" : "98",
      "icon" : "003061.png",
      "id" : "3640",
      "job" : "dark_knight",
      "levelReq" : "54",
      "name" : "Plunge"
    },
    "3641" : {
      "classCategory" : "98",
      "icon" : "003064.png",
      "id" : "3641",
      "job" : "dark_knight",
      "levelReq" : "56",
      "name" : "Abyssal Drain"
    },
    "3642" : {
      "classCategory" : "98",
      "icon" : "003067.png",
      "id" : "3642",
      "job" : "dark_knight",
      "levelReq" : "58",
      "name" : "Sole Survivor"
    },
    "3643" : {
      "classCategory" : "98",
      "icon" : "003058.png",
      "id" : "3643",
      "job" : "dark_knight",
      "levelReq" : "60",
      "name" : "Carve and Spit"
    },
    "4262" : {
      "classCategory" : "21",
      "icon" : "002536.png",
      "id" : "4262",
      "job" : "monk",
      "levelReq" : "52",
      "name" : "Form Shift"
    },
    "7381" : {
      "classCategory" : "20",
      "icon" : "002511.png",
      "id" : "7381",
      "job" : "paladin",
      "levelReq" : "46",
      "name" : "Total Eclipse"
    },
    "7382" : {
      "classCategory" : "20",
      "icon" : "002512.png",
      "id" : "7382",
      "job" : "paladin",
      "levelReq" : "62",
      "name" : "Intervention"
    },
    "7383" : {
      "classCategory" : "20",
      "icon" : "002513.png",
      "id" : "7383",
      "job" : "paladin",
      "levelReq" : "68",
      "name" : "Requiescat"
    },
    "7384" : {
      "classCategory" : "20",
      "icon" : "002514.png",
      "id" : "7384",
      "job" : "paladin",
      "levelReq" : "64",
      "name" : "Holy Spirit"
    },
    "7385" : {
      "classCategory" : "20",
      "icon" : "002515.png",
      "id" : "7385",
      "job" : "paladin",
      "levelReq" : "70",
      "name" : "Passage of Arms"
    },
    "7386" : {
      "classCategory" : "22",
      "icon" : "002561.png",
      "id" : "7386",
      "job" : "warrior",
      "levelReq" : "62",
      "name" : "Onslaught"
    },
    "7387" : {
      "classCategory" : "22",
      "icon" : "002562.png",
      "id" : "7387",
      "job" : "warrior",
      "levelReq" : "64",
      "name" : "Upheaval"
    },
    "7388" : {
      "classCategory" : "22",
      "icon" : "002563.png",
      "id" : "7388",
      "job" : "warrior",
      "levelReq" : "68",
      "name" : "Shake it Off"
    },
    "7389" : {
      "classCategory" : "22",
      "icon" : "002564.png",
      "id" : "7389",
      "job" : "warrior",
      "levelReq" : "70",
      "name" : "Inner Release"
    },
    "7390" : {
      "classCategory" : "98",
      "icon" : "003078.png",
      "id" : "7390",
      "job" : "dark_knight",
      "levelReq" : "62",
      "name" : "Delirium"
    },
    "7391" : {
      "classCategory" : "98",
      "icon" : "003079.png",
      "id" : "7391",
      "job" : "dark_knight",
      "levelReq" : "64",
      "name" : "Quietus"
    },
    "7392" : {
      "classCategory" : "98",
      "icon" : "003080.png",
      "id" : "7392",
      "job" : "dark_knight",
      "levelReq" : "68",
      "name" : "Bloodspiller"
    },
    "7393" : {
      "classCategory" : "98",
      "icon" : "003081.png",
      "id" : "7393",
      "job" : "dark_knight",
      "levelReq" : "70",
      "name" : "The Blackest Night"
    },
    "7394" : {
      "classCategory" : "21",
      "icon" : "002537.png",
      "id" : "7394",
      "job" : "monk",
      "levelReq" : "64",
      "name" : "Riddle of Earth"
    },
    "7395" : {
      "classCategory" : "21",
      "icon" : "002541.png",
      "id" : "7395",
      "job" : "monk",
      "levelReq" : "68",
      "name" : "Riddle of Fire"
    },
    "7396" : {
      "classCategory" : "21",
      "icon" : "002542.png",
      "id" : "7396",
      "job" : "monk",
      "levelReq" : "70",
      "name" : "Brotherhood"
    },
    "7397" : {
      "classCategory" : "23",
      "icon" : "002586.png",
      "id" : "7397",
      "job" : "dragoon",
      "levelReq" : "62",
      "name" : "Sonic Thrust"
    },
    "7398" : {
      "classCategory" : "23",
      "icon" : "002587.png",
      "id" : "7398",
      "job" : "dragoon",
      "levelReq" : "66",
      "name" : "Dragon Sight"
    },
    "7399" : {
      "classCategory" : "23",
      "icon" : "002588.png",
      "id" : "7399",
      "job" : "dragoon",
      "levelReq" : "68",
      "name" : "Mirage Dive"
    },
    "7400" : {
      "classCategory" : "23",
      "icon" : "002589.png",
      "id" : "7400",
      "job" : "dragoon",
      "levelReq" : "70",
      "name" : "Nastrond"
    },
    "7401" : {
      "classCategory" : "92",
      "icon" : "002920.png",
      "id" : "7401",
      "job" : "ninja",
      "levelReq" : "62",
      "name" : "Hellfrog Medium"
    },
    "7402" : {
      "classCategory" : "92",
      "icon" : "002921.png",
      "id" : "7402",
      "job" : "ninja",
      "levelReq" : "68",
      "name" : "Bhavacakra"
    },
    "7403" : {
      "classCategory" : "92",
      "icon" : "002922.png",
      "id" : "7403",
      "job" : "ninja",
      "levelReq" : "70",
      "name" : "Ten Chi Jin"
    },
    "7404" : {
      "classCategory" : "24",
      "icon" : "002611.png",
      "id" : "7404",
      "job" : "bard",
      "levelReq" : "52",
      "name" : "Pitch Perfect"
    },
    "7405" : {
      "classCategory" : "24",
      "icon" : "002612.png",
      "id" : "7405",
      "job" : "bard",
      "levelReq" : "62",
      "name" : "Troubadour"
    },
    "7406" : {
      "classCategory" : "24",
      "icon" : "002613.png",
      "id" : "7406",
      "job" : "bard",
      "levelReq" : "64",
      "name" : "Caustic Bite"
    },
    "7407" : {
      "classCategory" : "24",
      "icon" : "002614.png",
      "id" : "7407",
      "job" : "bard",
      "levelReq" : "64",
      "name" : "Stormbite"
    },
    "7408" : {
      "classCategory" : "24",
      "icon" : "002615.png",
      "id" : "7408",
      "job" : "bard",
      "levelReq" : "66",
      "name" : "Nature's Minne"
    },
    "7409" : {
      "classCategory" : "24",
      "icon" : "002616.png",
      "id" : "7409",
      "job" : "bard",
      "levelReq" : "70",
      "name" : "Refulgent Arrow"
    },
    "7410" : {
      "classCategory" : "96",
      "icon" : "003030.png",
      "id" : "7410",
      "job" : "machinist",
      "levelReq" : "62",
      "name" : "Cooldown"
    },
    "7414" : {
      "classCategory" : "96",
      "icon" : "003034.png",
      "id" : "7414",
      "job" : "machinist",
      "levelReq" : "66",
      "name" : "Barrel Stabilizer"
    },
    "7415" : {
      "classCategory" : "96",
      "icon" : "003035.png",
      "id" : "7415",
      "job" : "machinist",
      "levelReq" : "68",
      "name" : "Rook Overdrive"
    },
    "7416" : {
      "classCategory" : "96",
      "icon" : "003036.png",
      "id" : "7416",
      "job" : "machinist",
      "levelReq" : "68",
      "name" : "Rook Overload"
    },
    "7417" : {
      "classCategory" : "96",
      "icon" : "003037.png",
      "id" : "7417",
      "job" : "machinist",
      "levelReq" : "68",
      "name" : "Bishop Overload"
    },
    "7418" : {
      "classCategory" : "96",
      "icon" : "003038.png",
      "id" : "7418",
      "job" : "machinist",
      "levelReq" : "70",
      "name" : "Flamethrower"
    },
    "7419" : {
      "classCategory" : "26",
      "icon" : "002661.png",
      "id" : "7419",
      "job" : "black_mage",
      "levelReq" : "62",
      "name" : "Between the Lines"
    },
    "7420" : {
      "classCategory" : "26",
      "icon" : "002662.png",
      "id" : "7420",
      "job" : "black_mage",
      "levelReq" : "64",
      "name" : "Thunder IV"
    },
    "7421" : {
      "classCategory" : "26",
      "icon" : "002663.png",
      "id" : "7421",
      "job" : "black_mage",
      "levelReq" : "66",
      "name" : "Triplecast"
    },
    "7422" : {
      "classCategory" : "26",
      "icon" : "002664.png",
      "id" : "7422",
      "job" : "black_mage",
      "levelReq" : "70",
      "name" : "Foul"
    },
    "7423" : {
      "classCategory" : "28",
      "icon" : "002687.png",
      "id" : "7423",
      "job" : "summoner",
      "levelReq" : "64",
      "name" : "Aetherpact"
    },
    "7424" : {
      "classCategory" : "28",
      "icon" : "002689.png",
      "id" : "7424",
      "job" : "summoner",
      "levelReq" : "66",
      "name" : "Bio III"
    },
    "7425" : {
      "classCategory" : "28",
      "icon" : "002690.png",
      "id" : "7425",
      "job" : "summoner",
      "levelReq" : "66",
      "name" : "Miasma III"
    },
    "7426" : {
      "classCategory" : "28",
      "icon" : "002686.png",
      "id" : "7426",
      "job" : "summoner",
      "levelReq" : "62",
      "name" : "Ruin IV"
    },
    "7427" : {
      "classCategory" : "28",
      "icon" : "002691.png",
      "id" : "7427",
      "job" : "summoner",
      "levelReq" : "70",
      "name" : "Summon Bahamut"
    },
    "7429" : {
      "classCategory" : "28",
      "icon" : "002693.png",
      "id" : "7429",
      "job" : "summoner",
      "levelReq" : "70",
      "name" : "Enkindle Bahamut"
    },
    "7430" : {
      "classCategory" : "25",
      "icon" : "002636.png",
      "id" : "7430",
      "job" : "white_mage",
      "levelReq" : "62",
      "name" : "Thin Air"
    },
    "7431" : {
      "classCategory" : "25",
      "icon" : "002637.png",
      "id" : "7431",
      "job" : "white_mage",
      "levelReq" : "64",
      "name" : "Stone IV"
    },
    "7432" : {
      "classCategory" : "25",
      "icon" : "002638.png",
      "id" : "7432",
      "job" : "white_mage",
      "levelReq" : "66",
      "name" : "Divine Benison"
    },
    "7433" : {
      "classCategory" : "25",
      "icon" : "002639.png",
      "id" : "7433",
      "job" : "white_mage",
      "levelReq" : "70",
      "name" : "Plenary Indulgence"
    },
    "7434" : {
      "classCategory" : "29",
      "icon" : "002813.png",
      "id" : "7434",
      "job" : "scholar",
      "levelReq" : "62",
      "name" : "Excogitation"
    },
    "7435" : {
      "classCategory" : "29",
      "icon" : "002814.png",
      "id" : "7435",
      "job" : "scholar",
      "levelReq" : "64",
      "name" : "Broil II"
    },
    "7436" : {
      "classCategory" : "29",
      "icon" : "002815.png",
      "id" : "7436",
      "job" : "scholar",
      "levelReq" : "66",
      "name" : "Chain Strategem"
    },
    "7437" : {
      "classCategory" : "29",
      "icon" : "002816.png",
      "id" : "7437",
      "job" : "scholar",
      "levelReq" : "70",
      "name" : "Aetherpact"
    },
    "7438" : {
      "classCategory" : "29",
      "icon" : "002818.png",
      "id" : "7438",
      "job" : "scholar",
      "levelReq" : "70",
      "name" : "Fey Union"
    },
    "7439" : {
      "classCategory" : "99",
      "icon" : "003143.png",
      "id" : "7439",
      "job" : "astrologian",
      "levelReq" : "62",
      "name" : "Earthly Star"
    },
    "7442" : {
      "classCategory" : "99",
      "icon" : "003145.png",
      "id" : "7442",
      "job" : "astrologian",
      "levelReq" : "64",
      "name" : "Malefic III"
    },
    "7443" : {
      "classCategory" : "99",
      "icon" : "003106.png",
      "id" : "7443",
      "job" : "astrologian",
      "levelReq" : "66",
      "name" : "Minor Arcana"
    },
    "7447" : {
      "classCategory" : "55",
      "icon" : "000468.png",
      "id" : "7447",
      "job" : "thaumaturge",
      "levelReq" : "26",
      "name" : "Thunder II"
    },
    "7448" : {
      "classCategory" : "99",
      "icon" : "003107.png",
      "id" : "7448",
      "job" : "astrologian",
      "levelReq" : "70",
      "name" : "Sleeve Draw"
    },
    "7450" : {
      "classCategory" : "28",
      "icon" : "002688.png",
      "id" : "7450",
      "job" : "summoner",
      "levelReq" : "64",
      "name" : "Devotion"
    },
    "7477" : {
      "classCategory" : "111",
      "icon" : "003151.png",
      "id" : "7477",
      "job" : "samurai",
      "levelReq" : "1",
      "name" : "Hakaze"
    },
    "7478" : {
      "classCategory" : "111",
      "icon" : "003152.png",
      "id" : "7478",
      "job" : "samurai",
      "levelReq" : "4",
      "name" : "Jinpu"
    },
    "7479" : {
      "classCategory" : "111",
      "icon" : "003156.png",
      "id" : "7479",
      "job" : "samurai",
      "levelReq" : "18",
      "name" : "Shifu"
    },
    "7480" : {
      "classCategory" : "111",
      "icon" : "003166.png",
      "id" : "7480",
      "job" : "samurai",
      "levelReq" : "50",
      "name" : "Yukikaze"
    },
    "7481" : {
      "classCategory" : "111",
      "icon" : "003158.png",
      "id" : "7481",
      "job" : "samurai",
      "levelReq" : "30",
      "name" : "Gekko"
    },
    "7482" : {
      "classCategory" : "111",
      "icon" : "003164.png",
      "id" : "7482",
      "job" : "samurai",
      "levelReq" : "40",
      "name" : "Kasha"
    },
    "7483" : {
      "classCategory" : "111",
      "icon" : "003157.png",
      "id" : "7483",
      "job" : "samurai",
      "levelReq" : "26",
      "name" : "Fuga"
    },
    "7484" : {
      "classCategory" : "111",
      "icon" : "003163.png",
      "id" : "7484",
      "job" : "samurai",
      "levelReq" : "35",
      "name" : "Mangetsu"
    },
    "7485" : {
      "classCategory" : "111",
      "icon" : "003165.png",
      "id" : "7485",
      "job" : "samurai",
      "levelReq" : "45",
      "name" : "Oka"
    },
    "7486" : {
      "classCategory" : "111",
      "icon" : "003155.png",
      "id" : "7486",
      "job" : "samurai",
      "levelReq" : "15",
      "name" : "Enpi"
    },
    "7490" : {
      "classCategory" : "111",
      "icon" : "003173.png",
      "id" : "7490",
      "job" : "samurai",
      "levelReq" : "62",
      "name" : "Hissatsu: Shinten"
    },
    "7491" : {
      "classCategory" : "111",
      "icon" : "003174.png",
      "id" : "7491",
      "job" : "samurai",
      "levelReq" : "64",
      "name" : "Hissatsu: Kyuten"
    },
    "7492" : {
      "classCategory" : "111",
      "icon" : "003169.png",
      "id" : "7492",
      "job" : "samurai",
      "levelReq" : "54",
      "name" : "Hissatsu: Gyoten"
    },
    "7493" : {
      "classCategory" : "111",
      "icon" : "003170.png",
      "id" : "7493",
      "job" : "samurai",
      "levelReq" : "56",
      "name" : "Hissatsu: Gyoten"
    },
    "7494" : {
      "classCategory" : "111",
      "icon" : "003168.png",
      "id" : "7494",
      "job" : "samurai",
      "levelReq" : "52",
      "name" : "Hissatsu: Kaiten"
    },
    "7495" : {
      "classCategory" : "111",
      "icon" : "003176.png",
      "id" : "7495",
      "job" : "samurai",
      "levelReq" : "68",
      "name" : "Hagakure"
    },
    "7496" : {
      "classCategory" : "111",
      "icon" : "003177.png",
      "id" : "7496",
      "job" : "samurai",
      "levelReq" : "70",
      "name" : "Hissatsu: Guren"
    },
    "7497" : {
      "classCategory" : "111",
      "icon" : "003172.png",
      "id" : "7497",
      "job" : "samurai",
      "levelReq" : "60",
      "name" : "Meditate"
    },
    "7498" : {
      "classCategory" : "111",
      "icon" : "003153.png",
      "id" : "7498",
      "job" : "samurai",
      "levelReq" : "6",
      "name" : "Third Eye"
    },
    "7499" : {
      "classCategory" : "111",
      "icon" : "003167.png",
      "id" : "7499",
      "job" : "samurai",
      "levelReq" : "50",
      "name" : "Meikyo Shisui"
    },
    "7500" : {
      "classCategory" : "111",
      "icon" : "003154.png",
      "id" : "7500",
      "job" : "samurai",
      "levelReq" : "10",
      "name" : "Ageha"
    },
    "7501" : {
      "classCategory" : "111",
      "icon" : "003175.png",
      "id" : "7501",
      "job" : "samurai",
      "levelReq" : "66",
      "name" : "Hissatsu: Seigan"
    },
    "7502" : {
      "classCategory" : "111",
      "icon" : "003171.png",
      "id" : "7502",
      "job" : "samurai",
      "levelReq" : "58",
      "name" : "Merciful Eyes"
    },
    "7503" : {
      "classCategory" : "112",
      "icon" : "003202.png",
      "id" : "7503",
      "job" : "red_mage",
      "levelReq" : "2",
      "name" : "Jolt"
    },
    "7504" : {
      "classCategory" : "112",
      "icon" : "003201.png",
      "id" : "7504",
      "job" : "red_mage",
      "levelReq" : "1",
      "name" : "Riposte"
    },
    "7505" : {
      "classCategory" : "112",
      "icon" : "003203.png",
      "id" : "7505",
      "job" : "red_mage",
      "levelReq" : "4",
      "name" : "Verthunder"
    },
    "7506" : {
      "classCategory" : "112",
      "icon" : "003204.png",
      "id" : "7506",
      "job" : "red_mage",
      "levelReq" : "6",
      "name" : "Corps-a-corps"
    },
    "7507" : {
      "classCategory" : "112",
      "icon" : "003205.png",
      "id" : "7507",
      "job" : "red_mage",
      "levelReq" : "10",
      "name" : "Veraero"
    },
    "7508" : {
      "classCategory" : "112",
      "icon" : "003206.png",
      "id" : "7508",
      "job" : "red_mage",
      "levelReq" : "15",
      "name" : "Tether"
    },
    "7509" : {
      "classCategory" : "112",
      "icon" : "003207.png",
      "id" : "7509",
      "job" : "red_mage",
      "levelReq" : "18",
      "name" : "Scatter"
    },
    "7510" : {
      "classCategory" : "112",
      "icon" : "003208.png",
      "id" : "7510",
      "job" : "red_mage",
      "levelReq" : "26",
      "name" : "Verfire"
    },
    "7511" : {
      "classCategory" : "112",
      "icon" : "003209.png",
      "id" : "7511",
      "job" : "red_mage",
      "levelReq" : "30",
      "name" : "Verstone"
    },
    "7512" : {
      "classCategory" : "112",
      "icon" : "003210.png",
      "id" : "7512",
      "job" : "red_mage",
      "levelReq" : "35",
      "name" : "Zwerchhau"
    },
    "7513" : {
      "classCategory" : "112",
      "icon" : "003215.png",
      "id" : "7513",
      "job" : "red_mage",
      "levelReq" : "52",
      "name" : "Moulinet"
    },
    "7514" : {
      "classCategory" : "112",
      "icon" : "003216.png",
      "id" : "7514",
      "job" : "red_mage",
      "levelReq" : "54",
      "name" : "Vercure"
    },
    "7515" : {
      "classCategory" : "112",
      "icon" : "003211.png",
      "id" : "7515",
      "job" : "red_mage",
      "levelReq" : "40",
      "name" : "Displacement"
    },
    "7516" : {
      "classCategory" : "112",
      "icon" : "003213.png",
      "id" : "7516",
      "job" : "red_mage",
      "levelReq" : "50",
      "name" : "Redoublement"
    },
    "7517" : {
      "classCategory" : "112",
      "icon" : "003212.png",
      "id" : "7517",
      "job" : "red_mage",
      "levelReq" : "45",
      "name" : "Fleche"
    },
    "7518" : {
      "classCategory" : "112",
      "icon" : "003214.png",
      "id" : "7518",
      "job" : "red_mage",
      "levelReq" : "50",
      "name" : "Acceleration"
    },
    "7519" : {
      "classCategory" : "112",
      "icon" : "003217.png",
      "id" : "7519",
      "job" : "red_mage",
      "levelReq" : "56",
      "name" : "Contre Sixte"
    },
    "7520" : {
      "classCategory" : "112",
      "icon" : "003218.png",
      "id" : "7520",
      "job" : "red_mage",
      "levelReq" : "58",
      "name" : "Embolden"
    },
    "7521" : {
      "classCategory" : "112",
      "icon" : "003219.png",
      "id" : "7521",
      "job" : "red_mage",
      "levelReq" : "60",
      "name" : "Manafication"
    },
    "7522" : {
      "classCategory" : "112",
      "icon" : "003222.png",
      "id" : "7522",
      "job" : "red_mage",
      "levelReq" : "66",
      "name" : "Impact"
    },
    "7523" : {
      "classCategory" : "112",
      "icon" : "003221.png",
      "id" : "7523",
      "job" : "red_mage",
      "levelReq" : "64",
      "name" : "Verraise"
    },
    "7524" : {
      "classCategory" : "112",
      "icon" : "003220.png",
      "id" : "7524",
      "job" : "red_mage",
      "levelReq" : "62",
      "name" : "Jolt II"
    },
    "7525" : {
      "classCategory" : "112",
      "icon" : "003223.png",
      "id" : "7525",
      "job" : "red_mage",
      "levelReq" : "68",
      "name" : "Verflare"
    },
    "7526" : {
      "classCategory" : "112",
      "icon" : "003224.png",
      "id" : "7526",
      "job" : "red_mage",
      "levelReq" : "70",
      "name" : "Verholy"
    },
    "7531" : {
      "classCategory" : "113",
      "icon" : "000801.png",
      "id" : "7531",
      "job" : "tank",
      "levelReq" : "8",
      "name" : "Rampart"
    },
    "7532" : {
      "classCategory" : "113",
      "icon" : "000804.png",
      "id" : "7532",
      "job" : "tank",
      "levelReq" : "20",
      "name" : "Convalescence"
    },
    "7533" : {
      "classCategory" : "113",
      "icon" : "000803.png",
      "id" : "7533",
      "job" : "tank",
      "levelReq" : "16",
      "name" : "Provoke"
    },
    "7534" : {
      "classCategory" : "113",
      "icon" : "000807.png",
      "id" : "7534",
      "job" : "tank",
      "levelReq" : "36",
      "name" : "Awareness"
    },
    "7535" : {
      "classCategory" : "113",
      "icon" : "000806.png",
      "id" : "7535",
      "job" : "tank",
      "levelReq" : "32",
      "name" : "Reprisal"
    },
    "7536" : {
      "classCategory" : "113",
      "icon" : "000805.png",
      "id" : "7536",
      "job" : "tank",
      "levelReq" : "24",
      "name" : "Anticipation"
    },
    "7537" : {
      "classCategory" : "113",
      "icon" : "000810.png",
      "id" : "7537",
      "job" : "tank",
      "levelReq" : "48",
      "name" : "Shirk"
    },
    "7538" : {
      "classCategory" : "113",
      "icon" : "000808.png",
      "id" : "7538",
      "job" : "tank",
      "levelReq" : "40",
      "name" : "Interject"
    },
    "7539" : {
      "classCategory" : "113",
      "icon" : "000809.png",
      "id" : "7539",
      "job" : "tank",
      "levelReq" : "44",
      "name" : "Ultimatum"
    },
    "7540" : {
      "classCategory" : "113",
      "icon" : "000802.png",
      "id" : "7540",
      "job" : "tank",
      "levelReq" : "12",
      "name" : "Low Blow"
    },
    "7541" : {
      "classCategory" : "118",
      "icon" : "000821.png",
      "id" : "7541",
      "job" : "melee_dps",
      "levelReq" : "8",
      "name" : "Second Wind"
    },
    "7542" : {
      "classCategory" : "114",
      "icon" : "000823.png",
      "id" : "7542",
      "job" : "melee_dps",
      "levelReq" : "32",
      "name" : "Bloodbath"
    },
    "7543" : {
      "classCategory" : "114",
      "icon" : "000826.png",
      "id" : "7543",
      "job" : "melee_dps",
      "levelReq" : "36",
      "name" : "Goad"
    },
    "7544" : {
      "classCategory" : "118",
      "icon" : "000825.png",
      "id" : "7544",
      "job" : "melee_dps",
      "levelReq" : "24",
      "name" : "Invigorate"
    },
    "7545" : {
      "classCategory" : "119",
      "icon" : "000827.png",
      "id" : "7545",
      "job" : "melee_dps",
      "levelReq" : "20",
      "name" : "Diversion"
    },
    "7546" : {
      "classCategory" : "114",
      "icon" : "000830.png",
      "id" : "7546",
      "job" : "melee_dps",
      "levelReq" : "48",
      "name" : "True North"
    },
    "7547" : {
      "classCategory" : "114",
      "icon" : "000829.png",
      "id" : "7547",
      "job" : "melee_dps",
      "levelReq" : "44",
      "name" : "Crutch"
    },
    "7548" : {
      "classCategory" : "114",
      "icon" : "000822.png",
      "id" : "7548",
      "job" : "melee_dps",
      "levelReq" : "12",
      "name" : "Arm's Length"
    },
    "7549" : {
      "classCategory" : "114",
      "icon" : "000828.png",
      "id" : "7549",
      "job" : "melee_dps",
      "levelReq" : "40",
      "name" : "Feint"
    },
    "7550" : {
      "classCategory" : "115",
      "icon" : "000850.png",
      "id" : "7550",
      "job" : "ranged_dps",
      "levelReq" : "48",
      "name" : "Palisade"
    },
    "7551" : {
      "classCategory" : "115",
      "icon" : "000848.png",
      "id" : "7551",
      "job" : "ranged_dps",
      "levelReq" : "40",
      "name" : "Head Graze"
    },
    "7552" : {
      "classCategory" : "115",
      "icon" : "000849.png",
      "id" : "7552",
      "job" : "ranged_dps",
      "levelReq" : "44",
      "name" : "Arm Graze"
    },
    "7553" : {
      "classCategory" : "115",
      "icon" : "000842.png",
      "id" : "7553",
      "job" : "ranged_dps",
      "levelReq" : "12",
      "name" : "Foot Graze"
    },
    "7554" : {
      "classCategory" : "115",
      "icon" : "000843.png",
      "id" : "7554",
      "job" : "ranged_dps",
      "levelReq" : "16",
      "name" : "Leg Graze"
    },
    "7555" : {
      "classCategory" : "115",
      "icon" : "000846.png",
      "id" : "7555",
      "job" : "ranged_dps",
      "levelReq" : "32",
      "name" : "Tactician"
    },
    "7556" : {
      "classCategory" : "115",
      "icon" : "000847.png",
      "id" : "7556",
      "job" : "ranged_dps",
      "levelReq" : "36",
      "name" : "Refresh"
    },
    "7557" : {
      "classCategory" : "115",
      "icon" : "000844.png",
      "id" : "7557",
      "job" : "ranged_dps",
      "levelReq" : "20",
      "name" : "Peloton"
    },
    "7558" : {
      "classCategory" : "120",
      "icon" : "000862.png",
      "id" : "7558",
      "job" : "caster_dps",
      "levelReq" : "12",
      "name" : "Break"
    },
    "7559" : {
      "classCategory" : "120",
      "icon" : "000869.png",
      "id" : "7559",
      "job" : "caster_dps",
      "levelReq" : "44",
      "name" : "Surecast"
    },
    "7560" : {
      "classCategory" : "116",
      "icon" : "000861.png",
      "id" : "7560",
      "job" : "caster_dps",
      "levelReq" : "8",
      "name" : "Addle"
    },
    "7561" : {
      "classCategory" : "120",
      "icon" : "000866.png",
      "id" : "7561",
      "job" : "caster_dps",
      "levelReq" : "32",
      "name" : "Swiftcast"
    },
    "7562" : {
      "classCategory" : "120",
      "icon" : "000865.png",
      "id" : "7562",
      "job" : "caster_dps",
      "levelReq" : "24",
      "name" : "Lucid Dreaming"
    },
    "7563" : {
      "classCategory" : "116",
      "icon" : "000868.png",
      "id" : "7563",
      "job" : "caster_dps",
      "levelReq" : "40",
      "name" : "Apocatastasis"
    },
    "7564" : {
      "classCategory" : "116",
      "icon" : "000863.png",
      "id" : "7564",
      "job" : "caster_dps",
      "levelReq" : "16",
      "name" : "Drain"
    },
    "7565" : {
      "classCategory" : "116",
      "icon" : "000867.png",
      "id" : "7565",
      "job" : "caster_dps",
      "levelReq" : "36",
      "name" : "Mana Shift"
    },
    "7566" : {
      "classCategory" : "116",
      "icon" : "000870.png",
      "id" : "7566",
      "job" : "caster_dps",
      "levelReq" : "48",
      "name" : "Erase"
    },
    "7567" : {
      "classCategory" : "117",
      "icon" : "000881.png",
      "id" : "7567",
      "job" : "healer",
      "levelReq" : "8",
      "name" : "Cleric Stance"
    },
    "7568" : {
      "classCategory" : "117",
      "icon" : "000884.png",
      "id" : "7568",
      "job" : "healer",
      "levelReq" : "20",
      "name" : "Esuna"
    },
    "7569" : {
      "classCategory" : "117",
      "icon" : "000887.png",
      "id" : "7569",
      "job" : "healer",
      "levelReq" : "36",
      "name" : "Eye for an Eye"
    },
    "7570" : {
      "classCategory" : "117",
      "icon" : "000888.png",
      "id" : "7570",
      "job" : "healer",
      "levelReq" : "40",
      "name" : "Largesse"
    },
    "7571" : {
      "classCategory" : "117",
      "icon" : "000890.png",
      "id" : "7571",
      "job" : "healer",
      "levelReq" : "48",
      "name" : "Rescue"
    },
    "7572" : {
      "classCategory" : "117",
      "icon" : "000883.png",
      "id" : "7572",
      "job" : "healer",
      "levelReq" : "16",
      "name" : "Protect"
    },
    "7863" : {
      "classCategory" : "114",
      "icon" : "000824.png",
      "id" : "7863",
      "job" : "melee_dps",
      "levelReq" : "16",
      "name" : "Leg Sweep"
    },
    "7867" : {
      "classCategory" : "111",
      "icon" : "003159.png",
      "id" : "7867",
      "job" : "samurai",
      "levelReq" : "30",
      "name" : "Iaijutsu"
    },
    "9629" : {
      "classCategory" : "99",
      "icon" : "003108.png",
      "id" : "9629",
      "job" : "astrologian",
      "levelReq" : "30",
      "name" : "Undraw"
    },
    "16001" : {
      "icon" : "000525.png",
      "id" : "16001",
      "job" : "eos",
      "levelReq" : "1",
      "name" : "Sic"
    },
    "16002" : {
      "icon" : "000525.png",
      "id" : "16002",
      "job" : "selene",
      "levelReq" : "1",
      "name" : "Sic"
    },
    "16003" : {
      "icon" : "000525.png",
      "id" : "16003",
      "job" : "garuda-egi",
      "levelReq" : "1",
      "name" : "Sic"
    },
    "16004" : {
      "icon" : "000525.png",
      "id" : "16004",
      "job" : "titan-egi",
      "levelReq" : "1",
      "name" : "Sic"
    },
    "16005" : {
      "icon" : "000525.png",
      "id" : "16005",
      "job" : "ifrit-egi",
      "levelReq" : "1",
      "name" : "Sic"
    },
    "16011" : {
      "icon" : "000526.png",
      "id" : "16011",
      "job" : "eos",
      "levelReq" : "1",
      "name" : "Sic"
    },
    "16012" : {
      "icon" : "000526.png",
      "id" : "16012",
      "job" : "selene",
      "levelReq" : "1",
      "name" : "Sic"
    },
    "16013" : {
      "icon" : "000526.png",
      "id" : "16013",
      "job" : "garuda-egi",
      "levelReq" : "1",
      "name" : "Sic"
    },
    "16014" : {
      "icon" : "000526.png",
      "id" : "16014",
      "job" : "titan-egi",
      "levelReq" : "1",
      "name" : "Sic"
    },
    "16015" : {
      "icon" : "000526.png",
      "id" : "16015",
      "job" : "ifrit-egi",
      "levelReq" : "1",
      "name" : "Sic"
    },
    "16021" : {
      "icon" : "000529.png",
      "id" : "16021",
      "job" : "eos",
      "levelReq" : "1",
      "name" : "Heel"
    },
    "16022" : {
      "icon" : "000529.png",
      "id" : "16022",
      "job" : "selene",
      "levelReq" : "1",
      "name" : "Heel"
    },
    "16023" : {
      "icon" : "000529.png",
      "id" : "16023",
      "job" : "garuda-egi",
      "levelReq" : "1",
      "name" : "Heel"
    },
    "16024" : {
      "icon" : "000529.png",
      "id" : "16024",
      "job" : "titan-egi",
      "levelReq" : "1",
      "name" : "Heel"
    },
    "16025" : {
      "icon" : "000529.png",
      "id" : "16025",
      "job" : "ifrit-egi",
      "levelReq" : "1",
      "name" : "Heel"
    },
    "16031" : {
      "icon" : "000527.png",
      "id" : "16031",
      "job" : "eos",
      "levelReq" : "1",
      "name" : "Place"
    },
    "16032" : {
      "icon" : "000527.png",
      "id" : "16032",
      "job" : "selene",
      "levelReq" : "1",
      "name" : "Place"
    },
    "16033" : {
      "icon" : "000527.png",
      "id" : "16033",
      "job" : "garuda-egi",
      "levelReq" : "1",
      "name" : "Place"
    },
    "16034" : {
      "icon" : "000527.png",
      "id" : "16034",
      "job" : "titan-egi",
      "levelReq" : "1",
      "name" : "Place"
    },
    "16035" : {
      "icon" : "000527.png",
      "id" : "16035",
      "job" : "ifrit-egi",
      "levelReq" : "1",
      "name" : "Place"
    },
    "16041" : {
      "icon" : "000528.png",
      "id" : "16041",
      "job" : "eos",
      "levelReq" : "1",
      "name" : "Stay"
    },
    "16042" : {
      "icon" : "000528.png",
      "id" : "16042",
      "job" : "selene",
      "levelReq" : "1",
      "name" : "Stay"
    },
    "16043" : {
      "icon" : "000528.png",
      "id" : "16043",
      "job" : "garuda-egi",
      "levelReq" : "1",
      "name" : "Stay"
    },
    "16044" : {
      "icon" : "000528.png",
      "id" : "16044",
      "job" : "titan-egi",
      "levelReq" : "1",
      "name" : "Stay"
    },
    "16045" : {
      "icon" : "000528.png",
      "id" : "16045",
      "job" : "ifrit-egi",
      "levelReq" : "1",
      "name" : "Stay"
    },
    "7541b" : {
      "classCategory" : "118",
      "icon" : "000821.png",
      "id" : "7541",
      "job" : "ranged_dps",
      "levelReq" : "8",
      "name" : "Second Wind"
    },
    "7544b" : {
      "classCategory" : "118",
      "icon" : "000825.png",
      "id" : "7544b",
      "job" : "ranged_dps",
      "levelReq" : "24",
      "name" : "Invigorate"
    },
    "7545b" : {
      "classCategory" : "119",
      "icon" : "000827.png",
      "id" : "7545b",
      "job" : "caster_dps",
      "levelReq" : "20",
      "name" : "Diversion"
    },
    "7558b" : {
      "classCategory" : "120",
      "icon" : "000862.png",
      "id" : "7558b",
      "job" : "healer",
      "levelReq" : "12",
      "name" : "Break"
    },
    "7559b" : {
      "classCategory" : "120",
      "icon" : "000869.png",
      "id" : "7559b",
      "job" : "healer",
      "levelReq" : "44",
      "name" : "Surecast"
    },
    "7561b" : {
      "classCategory" : "120",
      "icon" : "000866.png",
      "id" : "7561b",
      "job" : "healer",
      "levelReq" : "32",
      "name" : "Swiftcast"
    },
    "7562b" : {
      "classCategory" : "120",
      "icon" : "000865.png",
      "id" : "7562b",
      "job" : "healer",
      "levelReq" : "24",
      "name" : "Lucid Dreaming"
    }
  },
  "crossBarTypes" : [ "standard", "LRRL", "LLRR" ],
  "jobs" : {
    "astrologian" : {
      "name" : "Astrologian",
      "relatedActionGroupIds" : [ "astrologian", "healer" ]
    },
    "bard" : {
      "name" : "Bard",
      "relatedActionGroupIds" : [ "archer", "bard", "ranged_dps" ]
    },
    "black_mage" : {
      "name" : "Black Mage",
      "relatedActionGroupIds" : [ "thaumaturge", "black_mage", "caster_dps" ]
    },
    "dark_knight" : {
      "name" : "Dark Knight",
      "relatedActionGroupIds" : [ "dark_knight", "tank" ]
    },
    "dragoon" : {
      "name" : "Dragoon",
      "relatedActionGroupIds" : [ "lancer", "dragoon", "melee_dps" ]
    },
    "machinist" : {
      "id" : 12,
      "name" : "Machinist",
      "relatedActionGroupIds" : [ "machinist", "ranged_dps" ]
    },
    "monk" : {
      "name" : "Monk",
      "relatedActionGroupIds" : [ "pugilist", "monk", "melee_dps" ]
    },
    "ninja" : {
      "name" : "Ninja",
      "relatedActionGroupIds" : [ "rogue", "ninja", "melee_dps" ]
    },
    "other_actions" : {
      "name" : "Other Actions",
      "relatedActionGroupIds" : [ "general", "main_menu", "pvp" ]
    },
    "paladin" : {
      "name" : "Paladin",
      "relatedActionGroupIds" : [ "gladiator", "paladin", "tank" ]
    },
    "red_mage" : {
      "name" : "Red Mage",
      "relatedActionGroupIds" : [ "red_mage", "caster_dps" ]
    },
    "samurai" : {
      "name" : "Samurai",
      "relatedActionGroupIds" : [ "samurai", "melee_dps" ]
    },
    "scholar" : {
      "name" : "Scholar",
      "relatedActionGroupIds" : [ "arcanist", "scholar", "eos", "selene", "pets", "healer" ]
    },
    "summoner" : {
      "name" : "Summoner",
      "relatedActionGroupIds" : [ "arcanist", "summoner", "garuda-egi", "titan-egi", "ifrit-egi", "pets", "caster_dps" ]
    },
    "warrior" : {
      "name" : "Warrior",
      "relatedActionGroupIds" : [ "marauder", "warrior", "tank" ]
    },
    "white_mage" : {
      "name" : "White Mage",
      "relatedActionGroupIds" : [ "conjurer", "white_mage", "healer" ]
    }
  }
}
